quadtreed3/__init__.py
quadtreed3/quadtreed3.py
quadtreed3-0.1.1.dist-info/LICENSE
quadtreed3-0.1.1.dist-info/METADATA
quadtreed3-0.1.1.dist-info/WHEEL
quadtreed3-0.1.1.dist-info/top_level.txt
quadtreed3-0.1.1.dist-info/RECORD
