Metadata-Version: 2.1
Name: quadtreed3
Version: 0.1.1
Summary: Quadtree implementation in Python following the d3-quadtree's structure
Home-page: https://github.com/xiaohk/quadtreed3
Author: Quadtree
Author-email: jay@zijie.wang
License: MIT license
Keywords: quadtreed3
Classifier: Development Status :: 2 - Pre-Alpha
Classifier: Intended Audience :: Developers
Classifier: License :: OSI Approved :: MIT License
Classifier: Natural Language :: English
Classifier: Programming Language :: Python :: 3
Classifier: Programming Language :: Python :: 3.9
Classifier: Programming Language :: Python :: 3.10
Classifier: Programming Language :: Python :: 3.11
Requires-Python: >=3.9
License-File: LICENSE
Requires-Dist: tqdm
Requires-Dist: numpy
